{
  "_class": "text",
  "attributedString": {
    "_class": "attributedString",
    "attributes": [
      {
        "_class": "stringAttribute",
        "attributes": {
          "MSAttributedStringColorAttribute": {
            "_class": "color",
            "alpha": 1,
            "blue": 0.2392156862745098,
            "green": 0.1607843137254902,
            "red": 0.07450980392156865
          },
          "MSAttributedStringFontAttribute": {
            "_class": "fontDescriptor",
            "attributes": {
              "name": "Kanit-Medium",
              "size": 10
            }
          },
          "MSAttributedStringTextTransformAttribute": 1,
          "kerning": 1.54,
          "paragraphStyle": {
            "_class": "paragraphStyle",
            "alignment": 0,
            "allowsDefaultTighteningForTruncation": 0,
            "maximumLineHeight": 13,
            "minimumLineHeight": 13
          },
          "strikethroughStyle": 0,
          "textStyleVerticalAlignmentKey": 0,
          "underlineStyle": 1
        },
        "length": 9,
        "location": 0
      }
    ],
    "string": "Read More"
  },
  "automaticallyDrawOnUnderlyingPath": false,
  "booleanOperation": -1,
  "clippingMaskMode": 0,
  "do_objectID": "262032D2-3065-4DD8-B05A-4ECE3BEF24D8",
  "dontSynchroniseWithSymbol": false,
  "exportOptions": {
    "_class": "exportOptions",
    "do_objectID": "229E07BD-9C76-4221-ACD7-17CD0F5D58DF",
    "exportFormats": [
    ],
    "includedLayerIds": [
    ],
    "layerOptions": 0,
    "shouldTrim": false
  },
  "frame": {
    "_class": "rect",
    "constrainProportions": false,
    "do_objectID": "C50772EB-13CD-4BA1-96CD-989604042AF0",
    "height": 13,
    "width": 198,
    "x": 13,
    "y": 223
  },
  "glyphBounds": "{{0, 3}, {67, 8}}",
  "hasClippingMask": false,
  "isFixedToViewport": false,
  "isFlippedHorizontal": false,
  "isFlippedVertical": false,
  "isLocked": false,
  "isVisible": true,
  "layerListExpandedType": 0,
  "lineSpacingBehaviour": 2,
  "maintainScrollPosition": false,
  "name": "Read More",
  "nameIsFixed": false,
  "resizingConstraint": 63,
  "resizingType": 0,
  "rotation": 0,
  "shouldBreakMaskChain": false,
  "style": {
    "_class": "style",
    "blur": {
      "_class": "blur",
      "center": "{0.5, 0.5}",
      "do_objectID": "31F15C46-D55B-4A93-B87E-AEFAA63712CD",
      "isEnabled": false,
      "motionAngle": 0,
      "radius": 10,
      "saturation": 1,
      "type": 0
    },
    "borderOptions": {
      "_class": "borderOptions",
      "dashPattern": [
      ],
      "do_objectID": "7B0EA06E-EF75-404C-8C7E-138E0138F7A8",
      "isEnabled": true,
      "lineCapStyle": 0,
      "lineJoinStyle": 0
    },
    "borders": [
    ],
    "colorControls": {
      "_class": "colorControls",
      "brightness": 0,
      "contrast": 1,
      "do_objectID": "53DAC959-BE7F-4E0F-BBAD-123B95DC4B48",
      "hue": 0,
      "isEnabled": true,
      "saturation": 1
    },
    "contextSettings": {
      "_class": "graphicsContextSettings",
      "blendMode": 0,
      "do_objectID": "E3BA929B-DCA9-45BE-8170-8082269B1C13",
      "opacity": 1
    },
    "do_objectID": "6D6A8D80-CB75-4A64-8210-0A2814CED167",
    "endMarkerType": 0,
    "fills": [
    ],
    "innerShadows": [
    ],
    "miterLimit": 10,
    "shadows": [
    ],
    "startMarkerType": 0,
    "textStyle": {
      "_class": "textStyle",
      "do_objectID": "CFB476DD-AB39-40F0-80CC-5344F5AB061F",
      "encodedAttributes": {
        "MSAttributedStringColorAttribute": {
          "_class": "color",
          "alpha": 1,
          "blue": 0.2392156862745098,
          "green": 0.1607843137254902,
          "red": 0.07450980392156865
        },
        "MSAttributedStringFontAttribute": {
          "_class": "fontDescriptor",
          "attributes": {
            "name": "Kanit-Medium",
            "size": 10
          }
        },
        "MSAttributedStringTextTransformAttribute": 1,
        "kerning": 1.54,
        "paragraphStyle": {
          "_class": "paragraphStyle",
          "alignment": 0,
          "allowsDefaultTighteningForTruncation": 0,
          "maximumLineHeight": 13,
          "minimumLineHeight": 13
        },
        "strikethroughStyle": 0,
        "textStyleVerticalAlignmentKey": 0,
        "underlineStyle": 1
      },
      "verticalAlignment": 0
    },
    "windingRule": 1
  },
  "textBehaviour": 1
}